Metadata-Version: 2.1
Name: optimize-tensorrt
Version: 1.0.1
Summary: Convert and inference TensorRT models
Home-page: https://github.com/riZZZhik/optimize_tensorrt
Author: Dmtry Barsukov
Author-email: riZZZhik@gmail.com
License: Apache
Platform: UNKNOWN
License-File: LICENSE
